rs_server_common/__init__.py
rs_server_common/authentication/apikey.py
rs_server_common/authentication/authentication.py
rs_server_common/authentication/authentication_to_external.py
rs_server_common/authentication/keycloak_util.py
rs_server_common/authentication/oauth2.py
rs_server_common/data_retrieval/__init__.py
rs_server_common/data_retrieval/eodag_provider.py
rs_server_common/data_retrieval/provider.py
rs_server_common/db/__init__.py
rs_server_common/db/database.py
rs_server_common/db/models/__init__.py
rs_server_common/db/models/download_status.py
rs_server_common/fastapi_app.py
rs_server_common/s3_storage_handler/__init__.py
rs_server_common/s3_storage_handler/s3_storage_handler.py
rs_server_common/schemas/__init__.py
rs_server_common/schemas/download_status_schema.py
rs_server_common/schemas/health_schema.py
rs_server_common/settings.py
rs_server_common/stac_api_common.py
rs_server_common/utils/__init__.py
rs_server_common/utils/logging.py
rs_server_common/utils/opentelemetry.py
rs_server_common/utils/pytest_utils.py
rs_server_common/utils/utils.py
rs_server_common/utils/utils2.py
rs_server_staging/__init__.py
rs_server_staging/config/config.yml
rs_server_staging/config/openapi.json
rs_server_staging/main.py
rs_server_staging/processors.py
rs_server_staging/rspy_models.py
rs_server_staging-99.99.dist-info/METADATA
rs_server_staging-99.99.dist-info/WHEEL
rs_server_staging-99.99.dist-info/RECORD
